Documentaion/test.v
/*module test;
        initial begin
            //$dumpfile("wave.vcd"); // Name of VCD file
            //$dumpvars(0, test);    // Dump all signals in 'test' module
            $display("Hello, Verilog!");
            $finish;
        end
endmodule
*/
module test2;
  reg clk;
  reg [3:0] counter;

  // Generate a clock signal
  always #5 clk = ~clk;

  initial begin
    // Enable VCD dump
    $dumpfile("wave.vcd"); // Name of VCD file
    $dumpvars(0, test2);    // Dump all signals in 'test' module

    // Initialize signals
    clk = 0;
    counter = 0;

    // Run for 10 clock cycles
    repeat (10) begin
      #10 counter = counter + 1;
    end

    $finish; // End simulation
  end
endmodule

Documentaion/wave.vcd
$date
	Wed Mar  5 12:12:29 2025
$end
$version
	Icarus Verilog
$end
$timescale
	1s
$end
$scope module test2 $end
$var reg 1 ! clk $end
$var reg 4 " counter [3:0] $end
$upscope $end
$enddefinitions $end
$comment Show the parameter values. $end
$dumpall
$end
#0
$dumpvars
b0 "
0!
$end
#5
1!
#10
0!
b1 "
#15
1!
#20
0!
b10 "
#25
1!
#30
0!
b11 "
#35
1!
#40
0!
b100 "
#45
1!
#50
0!
b101 "
#55
1!
#60
0!
b110 "
#65
1!
#70
0!
b111 "
#75
1!
#80
0!
b1000 "
#85
1!
#90
0!
b1001 "
#95
1!
#100
0!
b1010 "
