Lectures Computer Engineering/Verilog_Lecture01_Source_code.v
module lu_processor (
                        input clk,
                        input rst,
                        input [7:0] ICODE
                    );
    //==============================================
    //=============== STAGE 0 ======================
    //==============================================
    reg [7:0] S0_ADDR;

    reg [7:0] S1_ADDR;
    reg [7:0] S0_ADDR_MEM;
    reg [15:0] S4_WB_BYPASS_REGISTER;
    wire [15:0] RD_MEM_OUT;
    reg [15:0] S3_RESULT_REGISTER;
    reg S1_BYPASS_REG_CNTRL;
    wire [15:0] S3_S2S3DF_MUX;
    reg [15:0] S1_WB_BYPASS_RESULT;
    wire [15:0] S2_S0S3DF_MUX;
    wire [15:0] S2_S1S3DF_MUX;
    reg [7:0] S2_ADDR;
    reg [15:0] S2_MEM_OUT_REGISTER;
    reg [7:0] S3_ADDR;


    always@(posedge clk or posedge rst)begin
        if(rst)begin
            S0_ADDR <=8'b0;
            S0_ADDR_MEM <= 8'b0;
        end
        else begin
            S0_ADDR <= ICODE;
            S0_ADDR_MEM <= ICODE;
        end
    end
    //==============================================
    //=============== STAGE 1 ======================
    //==============================================
     always@(posedge clk or posedge rst)begin
        if(rst)begin
            S1_ADDR <=8'b0;
        end
        else begin
            S1_ADDR <= S0_ADDR;
        end
    end

    //Bypass register Control
    always@(posedge clk or posedge rst)begin
        if(rst)begin
            S1_BYPASS_REG_CNTRL <= 1'b0;
        end
        else if(S0_ADDR == S3_ADDR)begin
            S1_BYPASS_REG_CNTRL <= 1'b1;
        end
        else begin
            S1_BYPASS_REG_CNTRL <= S1_BYPASS_REG_CNTRL;
        end
    end

    //Dual port memory instantion
    syncMEM2P SyncMEM2P_instance1(
        //Port 0
        .ADDR0(S0_ADDR_MEM),
        .WD0(16'b0),
        .WE0(1'b0),
        .RD0(RD_MEM_OUT),

        //Port 1
        .ADDR1(S3_ADDR),
        .WD1(S3_RESULT_REGISTER),
        .WE1(1'b1),
        .RD1(),     //NO CONNECT

        //Common
        .CLK(clk)
    );
    //Write Back BYPASS REG
      always@(posedge clk or posedge rst)begin
        if(rst)begin
            S1_WB_BYPASS_RESULT <= 16'b0;
        end
        else begin
            S1_WB_BYPASS_RESULT <= S3_RESULT_REGISTER;
        end
    end
    //==============================================
    //=============== STAGE 2 ======================
    //==============================================
    always@(posedge clk or posedge rst)begin
        if(rst)begin
            S2_ADDR <= 8'b0;
        end
        else begin
            S2_ADDR <= S1_ADDR;
        end
    end

    //S0 - S3 data forwarding
    assign S2_S0S3DF_MUX = (S1_BYPASS_REG_CNTRL) ? S4_WB_BYPASS_REGISTER : RD_MEM_OUT;

    //S1 - S3 data forwarding
    assign S2_S1S3DF_MUX = (S1_ADDR == S3_ADDR) ? S3_RESULT_REGISTER : S2_S0S3DF_MUX;

    always@(posedge clk or posedge rst)begin
        if(rst)begin
            S2_MEM_OUT_REGISTER <= 16'b0;
        end
        else begin
            S2_MEM_OUT_REGISTER <= S2_S1S3DF_MUX;
        end
    end
    //==============================================
    //=============== STAGE 3 ======================
    //==============================================
    always@(posedge clk or posedge rst)begin
        if(rst)begin
            S3_ADDR <= 8'b0;
        end
        else begin
            S3_ADDR <= S2_ADDR;
        end
    end

    //S2 - S3 data forwarding
    assign S2_S2S3DF_MUX = (S2_ADDR == S3_ADDR) ? S3_RESULT_REGISTER : S2_MEM_OUT_REGISTER;

    always@(posedge clk or posedge rst)begin
        if(rst)begin
            S3_RESULT_REGISTER <= 16'b0;
        end
        else begin
            S3_RESULT_REGISTER <= S3_S2S3DF_MUX + 1'b1;
        end
    end
    //==============================================
    //=============== STAGE 4 ======================
    //==============================================
    always@(posedge clk or posedge rst)begin
        if(rst)begin
            S4_WB_BYPASS_REGISTER <= 1'b0;
        end
        else begin
            S4_WB_BYPASS_REGISTER <= S3_RESULT_REGISTER;
        end
    end
    //write back port is also S4 stage but instatiated in S1

endmodule

module syncMEM2P(
        //Port 0
        input   [7:0]  ADDR0,
        input   [15:0] WD0,
        input          WE0,
        output   [15:0] RD0,
        //Port 1
        input   [7:0]  ADDR1,
        input   [15:0] WD1,
        input          WE1,
        output   [15:0] RD1,
        //Common
        input CLK
    );
    reg [15:0] mem [0:255];
    integer i;
    //port 0
    reg [7:0] ADDR0_REG;
    always@(posedge CLK)begin
        if(WE0) mem[ADDR0] <= WD0;
        ADDR0_REG <= ADDR0;
    end
    assign RD0 = mem[ADDR0_REG];
    
    //port 1
    reg [7:0] ADDR1_REG;
    always@(posedge CLK)begin
        if(WE1) mem[ADDR1] <= WD1;
        ADDR1_REG <= ADDR1;
    end
    assign RD1 = mem[ADDR1_REG];
    
    initial begin
        #1000;
        i=0;
        for(i = 0; i< 256; i++)begin
            $display("%0d", mem[i]);
        end
    end 
endmodule

Lectures Computer Engineering/Test_bench_CPU.v
module Test_Bench_LU();

	reg clk;
	reg rst;
	reg[7:0] ICODE;
	reg[7:0] dsgn_stm[0:15];
	reg[3:0] addr_index;
    integer i;
    integer ii;
	
	lu_processor lu_proc(.clk(clk),
		     	     .rst(rst),
		     	     .ICODE(ICODE));

	initial begin
		clk = 0;
		forever begin
			#5;
			clk = ~clk;
		end
	end
	
	initial begin
		//$readmemb("stimulus.psj", dsgn_stm, 0);
		//$readmemb("mem_init.psj", lu_proc.SyncMEM2P_instance1.mem, 0);
        for(i = 0; i<16; i=i+1)begin
            dsgn_stm[i] = i;
        end
        for(ii = 0; ii<256; ii=ii+1)begin
            $display("ii=%0d",ii);
            lu_proc.SyncMEM2P_instance1.mem[ii] = 16'b0;
        end
		#1000;
		$finish();
	end
	
	initial begin
        $dumpfile("wave.vcd"); // Name of VCD file
        $dumpvars(3, Test_Bench_LU);    // Dump all signals in 'test' module
		addr_index = 0;
		rst = 1;//CPU in reset
		#12;
		rst = 0; //CPU active
		ICODE = 0;
		forever begin
			@(posedge clk);
			ICODE = dsgn_stm[addr_index];
			addr_index = addr_index+1;
		end
	end

	
endmodule

Lectures Computer Engineering/wave.vcd
$date
	Wed Mar  5 15:03:18 2025
$end
$version
	Icarus Verilog
$end
$timescale
	1s
$end
$scope module Test_Bench_LU $end
$var reg 8 ! ICODE [7:0] $end
$var reg 4 " addr_index [3:0] $end
$var reg 1 # clk $end
$var reg 1 $ rst $end
$var integer 32 % i [31:0] $end
$var integer 32 & ii [31:0] $end
$scope module lu_proc $end
$var wire 8 ' ICODE [7:0] $end
$var wire 16 ( S3_S2S3DF_MUX [15:0] $end
$var wire 1 # clk $end
$var wire 1 $ rst $end
$var wire 1 ) S2_S2S3DF_MUX $end
$var wire 16 * S2_S1S3DF_MUX [15:0] $end
$var wire 16 + S2_S0S3DF_MUX [15:0] $end
$var wire 16 , RD_MEM_OUT [15:0] $end
$var reg 8 - S0_ADDR [7:0] $end
$var reg 8 . S0_ADDR_MEM [7:0] $end
$var reg 8 / S1_ADDR [7:0] $end
$var reg 1 0 S1_BYPASS_REG_CNTRL $end
$var reg 16 1 S1_WB_BYPASS_RESULT [15:0] $end
$var reg 8 2 S2_ADDR [7:0] $end
$var reg 16 3 S2_MEM_OUT_REGISTER [15:0] $end
$var reg 8 4 S3_ADDR [7:0] $end
$var reg 16 5 S3_RESULT_REGISTER [15:0] $end
$var reg 16 6 S4_WB_BYPASS_REGISTER [15:0] $end
$scope module SyncMEM2P_instance1 $end
$var wire 8 7 ADDR0 [7:0] $end
$var wire 8 8 ADDR1 [7:0] $end
$var wire 1 # CLK $end
$var wire 16 9 RD0 [15:0] $end
$var wire 16 : RD1 [15:0] $end
$var wire 16 ; WD0 [15:0] $end
$var wire 16 < WD1 [15:0] $end
$var wire 1 = WE0 $end
$var wire 1 > WE1 $end
$var reg 8 ? ADDR0_REG [7:0] $end
$var reg 8 @ ADDR1_REG [7:0] $end
$var integer 32 A i [31:0] $end
$upscope $end
$upscope $end
$upscope $end
$enddefinitions $end
$comment Show the parameter values. $end
$dumpall
$end
#0
$dumpvars
bx A
bx @
bx ?
1>
0=
b0 <
b0 ;
bx :
bx 9
b0 8
b0 7
b0 6
b0 5
b0 4
b0 3
b0 2
b0 1
00
b0 /
b0 .
b0 -
bx ,
bx +
b0 *
0)
bz (
bx '
bx &
bx %
1$
0#
b0 "
bx !
$end
#1
b100000000 &
b10000 %
#5
b0 +
b0 ,
b0 9
b0 ?
b0 :
b0 @
1#
#10
0#
#12
b0 !
b0 '
0$
#15
x)
bx *
10
bx 5
bx <
b1 "
1#
#20
0#
#25
bx +
bx ,
bx 9
bx :
bx 6
bx 3
bx 1
b10 "
b1 !
b1 '
1#
#30
0#
#35
b1 .
b1 7
b1 -
b11 "
b10 !
b10 '
1#
#40
0#
#45
b0 ,
b0 9
b1 ?
b1 /
b10 .
b10 7
b10 -
b100 "
b11 !
b11 '
1#
#50
0#
#55
b10 ?
b11 .
b11 7
b11 -
b10 /
b1 2
b101 "
b100 !
b100 '
1#
#60
0#
#65
b11 ?
b1 4
b1 8
b10 2
b11 /
b100 .
b100 7
b100 -
b110 "
b101 !
b101 '
1#
#70
0#
#75
b1 @
b100 ?
b101 .
b101 7
b101 -
b100 /
b11 2
b10 4
b10 8
b111 "
b110 !
b110 '
1#
#80
0#
#85
b101 ?
b10 @
b11 4
b11 8
b100 2
b101 /
b110 .
b110 7
b110 -
b1000 "
b111 !
b111 '
1#
#90
0#
#95
b11 @
b110 ?
b111 .
b111 7
b111 -
b110 /
b101 2
b100 4
b100 8
b1001 "
b1000 !
b1000 '
1#
#100
0#
#105
b111 ?
b100 @
b101 4
b101 8
b110 2
b111 /
b1000 .
b1000 7
b1000 -
b1010 "
b1001 !
b1001 '
1#
#110
0#
#115
b101 @
b1000 ?
b1001 .
b1001 7
b1001 -
b1000 /
b111 2
b110 4
b110 8
b1011 "
b1010 !
b1010 '
1#
#120
0#
#125
b1001 ?
b110 @
b111 4
b111 8
b1000 2
b1001 /
b1010 .
b1010 7
b1010 -
b1100 "
b1011 !
b1011 '
1#
#130
0#
#135
b111 @
b1010 ?
b1011 .
b1011 7
b1011 -
b1010 /
b1001 2
b1000 4
b1000 8
b1101 "
b1100 !
b1100 '
1#
#140
0#
#145
b1011 ?
b1000 @
b1001 4
b1001 8
b1010 2
b1011 /
b1100 .
b1100 7
b1100 -
b1110 "
b1101 !
b1101 '
1#
#150
0#
#155
b1001 @
b1100 ?
b1101 .
b1101 7
b1101 -
b1100 /
b1011 2
b1010 4
b1010 8
b1111 "
b1110 !
b1110 '
1#
#160
0#
#165
b1101 ?
b1010 @
b1011 4
b1011 8
b1100 2
b1101 /
b1110 .
b1110 7
b1110 -
b0 "
b1111 !
b1111 '
1#
#170
0#
#175
b1011 @
b1110 ?
b1111 .
b1111 7
b1111 -
b1110 /
b1101 2
b1100 4
b1100 8
b1 "
b0 !
b0 '
1#
#180
0#
#185
b1111 ?
b1100 @
b1101 4
b1101 8
b1110 2
b1111 /
b0 .
b0 7
b0 -
b10 "
b1 !
b1 '
1#
#190
0#
#195
b1101 @
bx ,
bx 9
b0 ?
b1 .
b1 7
b1 -
b0 /
b1111 2
b1110 4
b1110 8
b11 "
b10 !
b10 '
1#
#200
0#
#205
b1 ?
b1110 @
b1111 4
b1111 8
b0 2
b1 /
b10 .
b10 7
b10 -
b100 "
b11 !
b11 '
1#
#210
0#
#215
b1111 @
b10 ?
b11 .
b11 7
b11 -
b10 /
b1 2
b0 4
b0 8
b101 "
b100 !
b100 '
1#
#220
0#
#225
b11 ?
b0 @
b1 4
b1 8
b10 2
b11 /
b100 .
b100 7
b100 -
b110 "
b101 !
b101 '
1#
#230
0#
#235
b1 @
b100 ?
b101 .
b101 7
b101 -
b100 /
b11 2
b10 4
b10 8
b111 "
b110 !
b110 '
1#
#240
0#
#245
b101 ?
b10 @
b11 4
b11 8
b100 2
b101 /
b110 .
b110 7
b110 -
b1000 "
b111 !
b111 '
1#
#250
0#
#255
b11 @
b110 ?
b111 .
b111 7
b111 -
b110 /
b101 2
b100 4
b100 8
b1001 "
b1000 !
b1000 '
1#
#260
0#
#265
b111 ?
b100 @
b101 4
b101 8
b110 2
b111 /
b1000 .
b1000 7
b1000 -
b1010 "
b1001 !
b1001 '
1#
#270
0#
#275
b101 @
b1000 ?
b1001 .
b1001 7
b1001 -
b1000 /
b111 2
b110 4
b110 8
b1011 "
b1010 !
b1010 '
1#
#280
0#
#285
b1001 ?
b110 @
b111 4
b111 8
b1000 2
b1001 /
b1010 .
b1010 7
b1010 -
b1100 "
b1011 !
b1011 '
1#
#290
0#
#295
b111 @
b1010 ?
b1011 .
b1011 7
b1011 -
b1010 /
b1001 2
b1000 4
b1000 8
b1101 "
b1100 !
b1100 '
1#
#300
0#
#305
b1011 ?
b1000 @
b1001 4
b1001 8
b1010 2
b1011 /
b1100 .
b1100 7
b1100 -
b1110 "
b1101 !
b1101 '
1#
#310
0#
#315
b1001 @
b1100 ?
b1101 .
b1101 7
b1101 -
b1100 /
b1011 2
b1010 4
b1010 8
b1111 "
b1110 !
b1110 '
1#
#320
0#
#325
b1101 ?
b1010 @
b1011 4
b1011 8
b1100 2
b1101 /
b1110 .
b1110 7
b1110 -
b0 "
b1111 !
b1111 '
1#
#330
0#
#335
b1011 @
b1110 ?
b1111 .
b1111 7
b1111 -
b1110 /
b1101 2
b1100 4
b1100 8
b1 "
b0 !
b0 '
1#
#340
0#
#345
b1111 ?
b1100 @
b1101 4
b1101 8
b1110 2
b1111 /
b0 .
b0 7
b0 -
b10 "
b1 !
b1 '
1#
#350
0#
#355
b1101 @
b0 ?
b1 .
b1 7
b1 -
b0 /
b1111 2
b1110 4
b1110 8
b11 "
b10 !
b10 '
1#
#360
0#
#365
b1 ?
b1110 @
b1111 4
b1111 8
b0 2
b1 /
b10 .
b10 7
b10 -
b100 "
b11 !
b11 '
1#
#370
0#
#375
b1111 @
b10 ?
b11 .
b11 7
b11 -
b10 /
b1 2
b0 4
b0 8
b101 "
b100 !
b100 '
1#
#380
0#
#385
b11 ?
b0 @
b1 4
b1 8
b10 2
b11 /
b100 .
b100 7
b100 -
b110 "
b101 !
b101 '
1#
#390
0#
#395
b1 @
b100 ?
b101 .
b101 7
b101 -
b100 /
b11 2
b10 4
b10 8
b111 "
b110 !
b110 '
1#
#400
0#
#405
b101 ?
b10 @
b11 4
b11 8
b100 2
b101 /
b110 .
b110 7
b110 -
b1000 "
b111 !
b111 '
1#
#410
0#
#415
b11 @
b110 ?
b111 .
b111 7
b111 -
b110 /
b101 2
b100 4
b100 8
b1001 "
b1000 !
b1000 '
1#
#420
0#
#425
b111 ?
b100 @
b101 4
b101 8
b110 2
b111 /
b1000 .
b1000 7
b1000 -
b1010 "
b1001 !
b1001 '
1#
#430
0#
#435
b101 @
b1000 ?
b1001 .
b1001 7
b1001 -
b1000 /
b111 2
b110 4
b110 8
b1011 "
b1010 !
b1010 '
1#
#440
0#
#445
b1001 ?
b110 @
b111 4
b111 8
b1000 2
b1001 /
b1010 .
b1010 7
b1010 -
b1100 "
b1011 !
b1011 '
1#
#450
0#
#455
b111 @
b1010 ?
b1011 .
b1011 7
b1011 -
b1010 /
b1001 2
b1000 4
b1000 8
b1101 "
b1100 !
b1100 '
1#
#460
0#
#465
b1011 ?
b1000 @
b1001 4
b1001 8
b1010 2
b1011 /
b1100 .
b1100 7
b1100 -
b1110 "
b1101 !
b1101 '
1#
#470
0#
#475
b1001 @
b1100 ?
b1101 .
b1101 7
b1101 -
b1100 /
b1011 2
b1010 4
b1010 8
b1111 "
b1110 !
b1110 '
1#
#480
0#
#485
b1101 ?
b1010 @
b1011 4
b1011 8
b1100 2
b1101 /
b1110 .
b1110 7
b1110 -
b0 "
b1111 !
b1111 '
1#
#490
0#
#495
b1011 @
b1110 ?
b1111 .
b1111 7
b1111 -
b1110 /
b1101 2
b1100 4
b1100 8
b1 "
b0 !
b0 '
1#
#500
0#
#505
b1111 ?
b1100 @
b1101 4
b1101 8
b1110 2
b1111 /
b0 .
b0 7
b0 -
b10 "
b1 !
b1 '
1#
#510
0#
#515
b1101 @
b0 ?
b1 .
b1 7
b1 -
b0 /
b1111 2
b1110 4
b1110 8
b11 "
b10 !
b10 '
1#
#520
0#
#525
b1 ?
b1110 @
b1111 4
b1111 8
b0 2
b1 /
b10 .
b10 7
b10 -
b100 "
b11 !
b11 '
1#
#530
0#
#535
b1111 @
b10 ?
b11 .
b11 7
b11 -
b10 /
b1 2
b0 4
b0 8
b101 "
b100 !
b100 '
1#
#540
0#
#545
b11 ?
b0 @
b1 4
b1 8
b10 2
b11 /
b100 .
b100 7
b100 -
b110 "
b101 !
b101 '
1#
#550
0#
#555
b1 @
b100 ?
b101 .
b101 7
b101 -
b100 /
b11 2
b10 4
b10 8
b111 "
b110 !
b110 '
1#
#560
0#
#565
b101 ?
b10 @
b11 4
b11 8
b100 2
b101 /
b110 .
b110 7
b110 -
b1000 "
b111 !
b111 '
1#
#570
0#
#575
b11 @
b110 ?
b111 .
b111 7
b111 -
b110 /
b101 2
b100 4
b100 8
b1001 "
b1000 !
b1000 '
1#
#580
0#
#585
b111 ?
b100 @
b101 4
b101 8
b110 2
b111 /
b1000 .
b1000 7
b1000 -
b1010 "
b1001 !
b1001 '
1#
#590
0#
#595
b101 @
b1000 ?
b1001 .
b1001 7
b1001 -
b1000 /
b111 2
b110 4
b110 8
b1011 "
b1010 !
b1010 '
1#
#600
0#
#605
b1001 ?
b110 @
b111 4
b111 8
b1000 2
b1001 /
b1010 .
b1010 7
b1010 -
b1100 "
b1011 !
b1011 '
1#
#610
0#
#615
b111 @
b1010 ?
b1011 .
b1011 7
b1011 -
b1010 /
b1001 2
b1000 4
b1000 8
b1101 "
b1100 !
b1100 '
1#
#620
0#
#625
b1011 ?
b1000 @
b1001 4
b1001 8
b1010 2
b1011 /
b1100 .
b1100 7
b1100 -
b1110 "
b1101 !
b1101 '
1#
#630
0#
#635
b1001 @
b1100 ?
b1101 .
b1101 7
b1101 -
b1100 /
b1011 2
b1010 4
b1010 8
b1111 "
b1110 !
b1110 '
1#
#640
0#
#645
b1101 ?
b1010 @
b1011 4
b1011 8
b1100 2
b1101 /
b1110 .
b1110 7
b1110 -
b0 "
b1111 !
b1111 '
1#
#650
0#
#655
b1011 @
b1110 ?
b1111 .
b1111 7
b1111 -
b1110 /
b1101 2
b1100 4
b1100 8
b1 "
b0 !
b0 '
1#
#660
0#
#665
b1111 ?
b1100 @
b1101 4
b1101 8
b1110 2
b1111 /
b0 .
b0 7
b0 -
b10 "
b1 !
b1 '
1#
#670
0#
#675
b1101 @
b0 ?
b1 .
b1 7
b1 -
b0 /
b1111 2
b1110 4
b1110 8
b11 "
b10 !
b10 '
1#
#680
0#
#685
b1 ?
b1110 @
b1111 4
b1111 8
b0 2
b1 /
b10 .
b10 7
b10 -
b100 "
b11 !
b11 '
1#
#690
0#
#695
b1111 @
b10 ?
b11 .
b11 7
b11 -
b10 /
b1 2
b0 4
b0 8
b101 "
b100 !
b100 '
1#
#700
0#
#705
b11 ?
b0 @
b1 4
b1 8
b10 2
b11 /
b100 .
b100 7
b100 -
b110 "
b101 !
b101 '
1#
#710
0#
#715
b1 @
b100 ?
b101 .
b101 7
b101 -
b100 /
b11 2
b10 4
b10 8
b111 "
b110 !
b110 '
1#
#720
0#
#725
b101 ?
b10 @
b11 4
b11 8
b100 2
b101 /
b110 .
b110 7
b110 -
b1000 "
b111 !
b111 '
1#
#730
0#
#735
b11 @
b110 ?
b111 .
b111 7
b111 -
b110 /
b101 2
b100 4
b100 8
b1001 "
b1000 !
b1000 '
1#
#740
0#
#745
b111 ?
b100 @
b101 4
b101 8
b110 2
b111 /
b1000 .
b1000 7
b1000 -
b1010 "
b1001 !
b1001 '
1#
#750
0#
#755
b101 @
b1000 ?
b1001 .
b1001 7
b1001 -
b1000 /
b111 2
b110 4
b110 8
b1011 "
b1010 !
b1010 '
1#
#760
0#
#765
b1001 ?
b110 @
b111 4
b111 8
b1000 2
b1001 /
b1010 .
b1010 7
b1010 -
b1100 "
b1011 !
b1011 '
1#
#770
0#
#775
b111 @
b1010 ?
b1011 .
b1011 7
b1011 -
b1010 /
b1001 2
b1000 4
b1000 8
b1101 "
b1100 !
b1100 '
1#
#780
0#
#785
b1011 ?
b1000 @
b1001 4
b1001 8
b1010 2
b1011 /
b1100 .
b1100 7
b1100 -
b1110 "
b1101 !
b1101 '
1#
#790
0#
#795
b1001 @
b1100 ?
b1101 .
b1101 7
b1101 -
b1100 /
b1011 2
b1010 4
b1010 8
b1111 "
b1110 !
b1110 '
1#
#800
0#
#805
b1101 ?
b1010 @
b1011 4
b1011 8
b1100 2
b1101 /
b1110 .
b1110 7
b1110 -
b0 "
b1111 !
b1111 '
1#
#810
0#
#815
b1011 @
b1110 ?
b1111 .
b1111 7
b1111 -
b1110 /
b1101 2
b1100 4
b1100 8
b1 "
b0 !
b0 '
1#
#820
0#
#825
b1111 ?
b1100 @
b1101 4
b1101 8
b1110 2
b1111 /
b0 .
b0 7
b0 -
b10 "
b1 !
b1 '
1#
#830
0#
#835
b1101 @
b0 ?
b1 .
b1 7
b1 -
b0 /
b1111 2
b1110 4
b1110 8
b11 "
b10 !
b10 '
1#
#840
0#
#845
b1 ?
b1110 @
b1111 4
b1111 8
b0 2
b1 /
b10 .
b10 7
b10 -
b100 "
b11 !
b11 '
1#
#850
0#
#855
b1111 @
b10 ?
b11 .
b11 7
b11 -
b10 /
b1 2
b0 4
b0 8
b101 "
b100 !
b100 '
1#
#860
0#
#865
b11 ?
b0 @
b1 4
b1 8
b10 2
b11 /
b100 .
b100 7
b100 -
b110 "
b101 !
b101 '
1#
#870
0#
#875
b1 @
b100 ?
b101 .
b101 7
b101 -
b100 /
b11 2
b10 4
b10 8
b111 "
b110 !
b110 '
1#
#880
0#
#885
b101 ?
b10 @
b11 4
b11 8
b100 2
b101 /
b110 .
b110 7
b110 -
b1000 "
b111 !
b111 '
1#
#890
0#
#895
b11 @
b110 ?
b111 .
b111 7
b111 -
b110 /
b101 2
b100 4
b100 8
b1001 "
b1000 !
b1000 '
1#
#900
0#
#905
b111 ?
b100 @
b101 4
b101 8
b110 2
b111 /
b1000 .
b1000 7
b1000 -
b1010 "
b1001 !
b1001 '
1#
#910
0#
#915
b101 @
b1000 ?
b1001 .
b1001 7
b1001 -
b1000 /
b111 2
b110 4
b110 8
b1011 "
b1010 !
b1010 '
1#
#920
0#
#925
b1001 ?
b110 @
b111 4
b111 8
b1000 2
b1001 /
b1010 .
b1010 7
b1010 -
b1100 "
b1011 !
b1011 '
1#
#930
0#
#935
b111 @
b1010 ?
b1011 .
b1011 7
b1011 -
b1010 /
b1001 2
b1000 4
b1000 8
b1101 "
b1100 !
b1100 '
1#
#940
0#
#945
b1011 ?
b1000 @
b1001 4
b1001 8
b1010 2
b1011 /
b1100 .
b1100 7
b1100 -
b1110 "
b1101 !
b1101 '
1#
#950
0#
#955
b1001 @
b1100 ?
b1101 .
b1101 7
b1101 -
b1100 /
b1011 2
b1010 4
b1010 8
b1111 "
b1110 !
b1110 '
1#
#960
0#
#965
b1101 ?
b1010 @
b1011 4
b1011 8
b1100 2
b1101 /
b1110 .
b1110 7
b1110 -
b0 "
b1111 !
b1111 '
1#
#970
0#
#975
b1011 @
b1110 ?
b1111 .
b1111 7
b1111 -
b1110 /
b1101 2
b1100 4
b1100 8
b1 "
b0 !
b0 '
1#
#980
0#
#985
b1111 ?
b1100 @
b1101 4
b1101 8
b1110 2
b1111 /
b0 .
b0 7
b0 -
b10 "
b1 !
b1 '
1#
#990
0#
#995
b1101 @
b0 ?
b1 .
b1 7
b1 -
b0 /
b1111 2
b1110 4
b1110 8
b11 "
b10 !
b10 '
1#
#1000
0#
b100000000 A
